shuttle_bus_rabbitmq/rabbitmq/__init__.py
shuttle_bus_rabbitmq/rabbitmq/basic_publisher.py
shuttle_bus_rabbitmq/rabbitmq/bus_control.py
shuttle_bus_rabbitmq/rabbitmq/configuration/__init__.py
shuttle_bus_rabbitmq/rabbitmq/configuration/bus_configuration.py
shuttle_bus_rabbitmq/rabbitmq/configurator/__init__.py
shuttle_bus_rabbitmq/rabbitmq/configurator/bus_factory_configurator.py
shuttle_bus_rabbitmq/rabbitmq/configurator/host_configurator.py
shuttle_bus_rabbitmq/rabbitmq/configurator/rabbitmq_connection_context_configurator.py
shuttle_bus_rabbitmq/rabbitmq/configurator/receive_endpoint_configurator.py
shuttle_bus_rabbitmq/rabbitmq/context/__init__.py
shuttle_bus_rabbitmq/rabbitmq/context/connection_context.py
shuttle_bus_rabbitmq/rabbitmq/context/model_context.py
shuttle_bus_rabbitmq/rabbitmq/example/__init__.py
shuttle_bus_rabbitmq/rabbitmq/example/consumer_handler.py
shuttle_bus_rabbitmq/rabbitmq/example/simple.py
shuttle_bus_rabbitmq/rabbitmq/factory/__init__.py
shuttle_bus_rabbitmq/rabbitmq/factory/bus_control_factory.py
shuttle_bus_rabbitmq/rabbitmq/factory/connection_context_factory.py
shuttle_bus_rabbitmq/rabbitmq/factory/connection_factory.py
shuttle_bus_rabbitmq/rabbitmq/factory/context_factory.py
shuttle_bus_rabbitmq/rabbitmq/factory/receive_settings_factory.py
shuttle_bus_rabbitmq/rabbitmq/README.md
shuttle_bus_rabbitmq/rabbitmq/setting/__init__.py
shuttle_bus_rabbitmq/rabbitmq/setting/endpoint_settings.py
shuttle_bus_rabbitmq/rabbitmq/setting/host_settings.py
shuttle_bus_rabbitmq/rabbitmq/setting/receive_settings.py
shuttle_bus_rabbitmq/rabbitmq/topology/__init__.py
shuttle_bus_rabbitmq/rabbitmq/topology/exchange.py
shuttle_bus_rabbitmq/rabbitmq/topology/queue.py
shuttle_bus_rabbitmq/rabbitmq/topology/queue_binding.py
shuttle_bus_rabbitmq-0.0.1.dist-info/LICENSE
shuttle_bus_rabbitmq-0.0.1.dist-info/WHEEL
shuttle_bus_rabbitmq-0.0.1.dist-info/METADATA
shuttle_bus_rabbitmq-0.0.1.dist-info/RECORD
