Metadata-Version: 2.1
Name: shuttle-bus-rabbitmq
Version: 0.0.1
Summary: 
Home-page: https://github.com/jbw/shuttle-bus
Keywords: shuttle-bus,rabbitmq,messaging
Author: Jason Watson
Author-email: jbw@jbw.cc
Requires-Python: >=3.6,<4.0
Classifier: License :: OSI Approved :: Apache Software License
Classifier: Operating System :: OS Independent
Classifier: Programming Language :: Python :: 3
Classifier: Programming Language :: Python :: 3.6
Classifier: Programming Language :: Python :: 3.7
Classifier: Programming Language :: Python :: 3.8
Classifier: Programming Language :: Python :: 3.9
Requires-Dist: aio_pika (>=6.6.0,<7.0.0)
Requires-Dist: typing_extensions (>=3.7.4,<4.0.0)
Project-URL: Repository, https://github.com/jbw/shuttle-bus
